[ 
    {
        "title": "Titulo Nuevo 11111",
        "tasks": [
            { "taskTitle": "Task 1!", "isFinished": false },
            { "taskTitle": "Tasl 222222222", "isFinished": false },
            { "taskTitle": "Task 3", "isFinished": false }
    ]
    },
    {
        "title": "Titulo Nuevo 22222",
        "tasks": [
            { "taskTitle": "Task 91", "isFinished": false },
            { "taskTitle": "Task 8 2", "isFinished": false },
            { "taskTitle": "TAskkk 3", "isFinished": false }
        ]
    }
]